pynsee/__init__.py
pynsee/constants.py
pynsee/download/__init__.py
pynsee/download/_check_url.py
pynsee/download/_download_pb.py
pynsee/download/_download_store_file.py
pynsee/download/_get_dict_data_source.py
pynsee/download/_get_file_list_internal.py
pynsee/download/_get_value_label.py
pynsee/download/_import_options.py
pynsee/download/_load_data_from_schema.py
pynsee/download/_unzip_pb.py
pynsee/download/download_file.py
pynsee/download/get_column_metadata.py
pynsee/download/get_file_list.py
pynsee/download/data/__init__.py
pynsee/download/data/liste_donnees.zip
pynsee/geodata/__init__.py
pynsee/geodata/_add_insee_dep.py
pynsee/geodata/_distance.py
pynsee/geodata/_find_wfs_closest_match.py
pynsee/geodata/_geojson_parser.py
pynsee/geodata/_get_bbox_list.py
pynsee/geodata/_get_bbox_list_full.py
pynsee/geodata/_get_capabilities.py
pynsee/geodata/_get_center.py
pynsee/geodata/_get_data_with_bbox.py
pynsee/geodata/_get_full_list_wfs.py
pynsee/geodata/_get_geodata.py
pynsee/geodata/_get_geodata_with_backup.py
pynsee/geodata/_make_offshore_points.py
pynsee/geodata/_rescale_geom.py
pynsee/geodata/geofrdataframe.py
pynsee/geodata/get_geodata.py
pynsee/geodata/get_geodata_list.py
pynsee/geodata/get_geom.py
pynsee/geodata/translate_and_zoom.py
pynsee/localdata/__init__.py
pynsee/localdata/_find_latest_local_dataset.py
pynsee/localdata/_get_geo_list_simple.py
pynsee/localdata/_get_geo_relation.py
pynsee/localdata/_get_insee_local_onegeo.py
pynsee/localdata/_get_insee_one_area.py
pynsee/localdata/_warning_local_data.py
pynsee/localdata/get_area_list.py
pynsee/localdata/get_area_projection.py
pynsee/localdata/get_ascending_area.py
pynsee/localdata/get_descending_area.py
pynsee/localdata/get_geo_list.py
pynsee/localdata/get_local_data.py
pynsee/localdata/get_local_metadata.py
pynsee/localdata/get_new_city.py
pynsee/localdata/get_nivgeo_list.py
pynsee/localdata/get_old_city.py
pynsee/localdata/get_population.py
pynsee/localdata/data/__init__.py
pynsee-0.2.4.dist-info/licenses/LICENSE.md
pynsee-0.2.4.dist-info/METADATA
pynsee-0.2.4.dist-info/WHEEL
pynsee-0.2.4.dist-info/top_level.txt
pynsee-0.2.4.dist-info/RECORD
