Metadata-Version: 2.4
Name: pynsee
Version: 0.2.4
Summary: Tools to Easily Search and Download French Data From INSEE and IGN APIs.
Author-email: Hadrien Leclerc <leclerc.hadrien@gmail.com>, Lino Galiana <lino.galiana@insee.fr>, Thomas Grandjean <thomas.grandjean@developpement-durable.gouv.fr>, Tanguy Fardet <tanguy.fardet@ens-lyon.org>
License: The MIT License (MIT)
Project-URL: repository, https://github.com/InseeFrLab/pynsee
Project-URL: bug-tracker, https://github.com/InseeFrLab/pynsee/issues
Project-URL: documentation, https://pynsee.readthedocs.io
Keywords: INSEE,IGN,statistics,demography,geospatial,France,GIS,statistique,démographie,géospatial,SIG
Classifier: Development Status :: 5 - Production/Stable
Classifier: Intended Audience :: Science/Research
Classifier: Intended Audience :: Information Technology
Classifier: Intended Audience :: Education
Classifier: Intended Audience :: Other Audience
Classifier: License :: OSI Approved :: MIT License
Classifier: Programming Language :: Python
Classifier: Programming Language :: Python :: 3
Classifier: Operating System :: OS Independent
Classifier: Natural Language :: English
Classifier: Topic :: Scientific/Engineering :: Information Analysis
Classifier: Topic :: Scientific/Engineering :: GIS
Requires-Python: >=3.9
License-File: LICENSE.md
Requires-Dist: pandas<3.0,>=2.2.0
Requires-Dist: geopandas<2.0,>=1.0
Requires-Dist: pyarrow>=17.0
Requires-Dist: tqdm>=4.56
Requires-Dist: platformdirs>=4
Requires-Dist: unidecode>=1.3
Requires-Dist: urllib3>=2.2
Requires-Dist: shapely>=2
Requires-Dist: requests>=2.32
Requires-Dist: requests-ratelimiter>=0.7
Requires-Dist: openpyxl
Provides-Extra: full
Requires-Dist: pandas<3.0,>=2.2.0; extra == "full"
Requires-Dist: geopandas<2.0,>=1.0; extra == "full"
Requires-Dist: pyarrow>=17.0; extra == "full"
Requires-Dist: tqdm>=4.56; extra == "full"
Requires-Dist: platformdirs>=4; extra == "full"
Requires-Dist: unidecode>=1.3; extra == "full"
Requires-Dist: urllib3>=2.2; extra == "full"
Requires-Dist: shapely>=2; extra == "full"
Requires-Dist: requests>=2.32; extra == "full"
Requires-Dist: requests-ratelimiter>=0.7; extra == "full"
Requires-Dist: openpyxl; extra == "full"
Requires-Dist: xlrd>2.0; extra == "full"
Dynamic: license-file
